injectionkit/__init__.py
injectionkit/_app.py
injectionkit/_container.py
injectionkit/_option.py
injectionkit/reflect/__init__.py
injectionkit/reflect/_function.py
injectionkit/reflect/_type.py
injectionkit-1.3.3.dist-info/METADATA
injectionkit-1.3.3.dist-info/WHEEL
injectionkit-1.3.3.dist-info/licenses/LICENSE
injectionkit-1.3.3.dist-info/RECORD
